{
  "id": "sun-annieposting",
  "repo_url": "",
  "viewer_url": "",
  "manifest_url": "",
  "museum_copy": {
    "title": "@annieposting Solar Museum",
    "subtitle": "Community Archive proof-of-search map.",
    "warning": "Archive terrain, not reputation. Raw coverage ends where the archive/upload/API ends."
  },
  "sun": {
    "id": "sun_b8f223532a13",
    "display_name": "annieposting",
    "user_id": "@annieposting",
    "description": "Community Archive-derived proof-of-search sun for @annieposting.",
    "document_count": 40101,
    "word_count": 637461,
    "active_days": 1675,
    "emissions": [
      "Think",
      "Don",
      "Good",
      "Only",
      "Time",
      "Should"
    ],
    "generated_at": "2026-06-29T18:01:32.142512+00:00",
    "color": "#f59e0b",
    "mass": 163.379,
    "density": 0.6473,
    "semantic_density": 0.6473,
    "semantic_dispersion": 0.3527,
    "embedding": [
      0.017557,
      -0.093023,
      0.002881,
      0.0,
      0.073788,
      0.009973,
      0.01116,
      -0.005355,
      -0.002054,
      -0.010534,
      0.02653,
      -0.074225,
      0.043899,
      -0.024336,
      -0.118697,
      -0.00592,
      -0.000912,
      -0.013209,
      0.015945,
      0.022771,
      0.069719,
      -0.018697,
      -0.028267,
      -0.009884,
      0.003999,
      0.28658,
      0.349788,
      -0.308869,
      -0.009427,
      0.040376,
      -0.030085,
      -0.018142,
      0.355814,
      0.003041,
      0.033795,
      -0.100008,
      0.0394,
      -0.007407,
      0.261995,
      -0.328846,
      -0.001108,
      0.112251,
      -0.034479,
      0.025684,
      -0.108464,
      0.035183,
      0.356916,
      0.002762,
      -0.33396,
      -0.028687,
      0.052206,
      -0.03281,
      -0.137822,
      -0.010935,
      0.088537,
      -0.020084,
      0.010121,
      0.114777,
      0.008905,
      0.001005,
      0.150706,
      0.041689,
      -0.01154,
      0.003503
    ],
    "embedding_backend": "stable-token-hash-v1",
    "embedding_dimensions": 64,
    "embedding_document_count": 93,
    "planet_mass_sum": 142.896,
    "mass_rule": "sun mass is the topic-planet mass field plus multi-planet gravity bonus; semantic density is embedding compactness of the corpus surface"
  },
  "planets": [
    {
      "id": "planet_41591d408bea",
      "name": "Think",
      "summary": "Archive cluster around think: 35576 posts; 4 quote-backed receipts pinned.",
      "top_terms": [
        "think",
        "elytramithra",
        "love",
        "could",
        "mallorymable"
      ],
      "artifacts": [
        {
          "id": "art_4bf56500cce1",
          "title": "Think receipt from 2025-07-31",
          "excerpt": "for reference this woman is a former CIA agent who once addressed a critic's dogs by name in order to intimidate him, shortly before he wound up dead",
          "source_document_id": "1951041077047390254",
          "timestamp": "2025-07-31T22:03:36+00:00",
          "url": "https://x.com/annieposting/status/1951041077047390254",
          "proof_of_search": "Community Archive row → normalized post → topic planet. Terms: think, elytramithra, love, could."
        },
        {
          "id": "art_53c062d31daf",
          "title": "Think receipt from 2026-03-01",
          "excerpt": "losing my shit at multiple californian cities being incapable of portraying alyssa liu as the correct race https://t.co/J06NWxcz1N",
          "source_document_id": "2027908985639305401",
          "timestamp": "2026-03-01T00:49:13+00:00",
          "url": "https://x.com/annieposting/status/2027908985639305401",
          "proof_of_search": "Community Archive row → normalized post → topic planet. Terms: think, elytramithra, love, could."
        },
        {
          "id": "art_df2b111a91e3",
          "title": "Think receipt from 2026-03-14",
          "excerpt": "woman on the Amtrak started freaking out and losing her shit at me out of nowhere because she claimed when I was sitting and silently looking out the window with airpods in, I was actually secretly recording her on my phone.\n\nconductor walks by and she loudly explains the situation and without skipping a beat he just goes \"he's here every week and this is the first complaint I've gotten, you can get off at the next stop\"\n\nshout out Keith you a real one",
          "source_document_id": "2032929543640723519",
          "timestamp": "2026-03-14T21:19:07+00:00",
          "url": "https://x.com/annieposting/status/2032929543640723519",
          "proof_of_search": "Community Archive row → normalized post → topic planet. Terms: think, elytramithra, love, could."
        },
        {
          "id": "art_194e88b64410",
          "title": "Think receipt from 2025-08-14",
          "excerpt": "RT @WesleyBout: Went to get a Covid test and a giant broccoli man walked by the door https://t.co/P4lwT6xPYI",
          "source_document_id": "1956091552335585503",
          "timestamp": "2025-08-14T20:32:23+00:00",
          "url": "https://x.com/annieposting/status/1956091552335585503",
          "proof_of_search": "Community Archive row → normalized post → topic planet. Terms: think, elytramithra, love, could."
        }
      ],
      "artifact_count": 4,
      "receipt_id": "rcpt_526e960aa1c4",
      "proof_score": 1,
      "mass": 28.195,
      "color": "#14b8a6",
      "cluster_id": 0,
      "density": 0.7866,
      "semantic_density": 0.7866,
      "semantic_dispersion": 0.2134,
      "embedding": [
        0.0,
        -0.039286,
        0.0,
        -0.033575,
        0.029077,
        0.0,
        0.037735,
        -0.018867,
        0.0,
        0.0,
        -0.018867,
        -0.241942,
        0.010209,
        -0.047944,
        -0.033575,
        -0.018867,
        -0.018867,
        0.031084,
        0.0,
        0.05445,
        0.037735,
        0.0,
        -0.035244,
        -0.047461,
        -0.018867,
        0.0,
        -0.775228,
        -0.23572,
        0.0,
        -0.029077,
        0.0,
        -0.004498,
        -0.018867,
        0.0,
        -0.029077,
        -0.095888,
        0.0,
        0.0,
        0.189928,
        0.0,
        -0.033575,
        0.018867,
        0.0,
        -0.018867,
        -0.068363,
        0.021358,
        0.304539,
        0.0,
        0.0,
        0.0,
        0.029077,
        -0.047944,
        -0.029077,
        0.0,
        0.223075,
        0.0,
        0.0,
        0.241942,
        0.033575,
        0.0,
        0.018867,
        -0.052014,
        0.0,
        0.047944
      ],
      "embedding_backend": "stable-token-hash-v1",
      "embedding_dimensions": 64,
      "embedding_document_count": 15,
      "mass_rule": "blended historical topic volume with stable-token-hash embedding density; compact semantic clusters pull harder than diffuse receipt piles",
      "mass_rank": 1,
      "mass_share_of_sun": 0.17257,
      "relative_mass_to_largest_planet": 1.0,
      "radius_scale": 1.0
    },
    {
      "id": "planet_d1876c1d087e",
      "name": "Don",
      "summary": "Archive cluster around don: 1085 posts; 4 quote-backed receipts pinned.",
      "top_terms": [
        "don",
        "know",
        "want",
        "any",
        "say"
      ],
      "artifacts": [
        {
          "id": "art_7706faba2dd8",
          "title": "Don receipt from 2026-02-03",
          "excerpt": "RT @dummystupidgirl: sex is a very sacred and intimate act.\n\ndon’t do it with someone ever under any circumstances no matter what.",
          "source_document_id": "2018582905879158994",
          "timestamp": "2026-02-03T07:10:42+00:00",
          "url": "https://x.com/annieposting/status/2018582905879158994",
          "proof_of_search": "Community Archive row → normalized post → topic planet. Terms: don, know, want, any."
        },
        {
          "id": "art_8e8c22e93565",
          "title": "Don receipt from 2026-05-20",
          "excerpt": "RT @BenisXDDDDDD: *talking to a non-age gap couple*\n\"I don't understand, so who is the pedophile and who is the child?\"",
          "source_document_id": "2056939204664578460",
          "timestamp": "2026-05-20T03:24:57+00:00",
          "url": "https://x.com/annieposting/status/2056939204664578460",
          "proof_of_search": "Community Archive row → normalized post → topic planet. Terms: don, know, want, any."
        },
        {
          "id": "art_4698fd4c7eda",
          "title": "Don receipt from 2025-05-03",
          "excerpt": "RT @arbresmuets: “don’t upend your life for a girl” &lt;- are you insane? what else am i supposed to upend my life for? a job? rot in hell.",
          "source_document_id": "1918785444575142002",
          "timestamp": "2025-05-03T21:51:13+00:00",
          "url": "https://x.com/annieposting/status/1918785444575142002",
          "proof_of_search": "Community Archive row → normalized post → topic planet. Terms: don, know, want, any."
        },
        {
          "id": "art_5413ed61d798",
          "title": "Don receipt from 2025-12-31",
          "excerpt": "RT @mauddweeb: Wife: You know you don’t have to say everything that comes to mind right? \n\n Me: Have you considered that I don’t.\n\nWife: Oh…",
          "source_document_id": "2006154341820809509",
          "timestamp": "2025-12-31T00:04:02+00:00",
          "url": "https://x.com/annieposting/status/2006154341820809509",
          "proof_of_search": "Community Archive row → normalized post → topic planet. Terms: don, know, want, any."
        }
      ],
      "artifact_count": 4,
      "receipt_id": "rcpt_a1ed0a827a86",
      "proof_score": 1,
      "mass": 23.178,
      "color": "#f59e0b",
      "cluster_id": 1,
      "density": 0.8238,
      "semantic_density": 0.8238,
      "semantic_dispersion": 0.1762,
      "embedding": [
        0.0,
        -0.051469,
        -0.029715,
        0.0,
        0.051469,
        0.03623,
        -0.03623,
        -0.034175,
        0.0,
        -0.029715,
        0.0,
        0.006514,
        0.0,
        0.0,
        -0.225786,
        0.0,
        0.0,
        -0.029715,
        0.029715,
        0.03623,
        0.062267,
        0.0,
        0.0,
        0.0,
        0.0,
        0.862393,
        0.145575,
        -0.11586,
        0.0,
        0.042359,
        0.0,
        0.185096,
        0.0,
        0.0,
        0.034175,
        -0.034175,
        0.0,
        0.032552,
        0.145575,
        0.0,
        0.0,
        0.046035,
        0.0,
        0.0,
        -0.051469,
        0.032552,
        0.190482,
        0.032552,
        -0.044906,
        0.0,
        0.0,
        0.0,
        0.034175,
        0.034175,
        -0.032552,
        -0.032552,
        0.0,
        0.062267,
        0.029715,
        0.002836,
        0.0,
        0.191611,
        -0.032552,
        0.0
      ],
      "embedding_backend": "stable-token-hash-v1",
      "embedding_dimensions": 64,
      "embedding_document_count": 15,
      "mass_rule": "blended historical topic volume with stable-token-hash embedding density; compact semantic clusters pull harder than diffuse receipt piles",
      "mass_rank": 3,
      "mass_share_of_sun": 0.14187,
      "relative_mass_to_largest_planet": 0.82206,
      "radius_scale": 0.9552
    },
    {
      "id": "planet_354e31146825",
      "name": "Good",
      "summary": "Archive cluster around good: 1087 posts; 4 quote-backed receipts pinned.",
      "top_terms": [
        "good",
        "really",
        "bad",
        "thing",
        "girl"
      ],
      "artifacts": [
        {
          "id": "art_c52439c33985",
          "title": "Good receipt from 2025-08-27",
          "excerpt": "RT @tomwalkerisgood: KOKO: Koko birkin bag. Practical Koko possession bag\nRESEARCHER: No, Koko. You can’t have a Birkin bag.\nKOKO: Good Bir…",
          "source_document_id": "1960495158753149338",
          "timestamp": "2025-08-27T00:10:44+00:00",
          "url": "https://x.com/annieposting/status/1960495158753149338",
          "proof_of_search": "Community Archive row → normalized post → topic planet. Terms: good, really, bad, thing."
        },
        {
          "id": "art_0e2ed2459cce",
          "title": "Good receipt from 2025-06-30",
          "excerpt": "RT @jarvis_best: The UK speech laws are interesting because you can get VIP tickets to see Kill Whitey at the Nine Eleven Was Good Fest but…",
          "source_document_id": "1939768461229711697",
          "timestamp": "2025-06-30T19:30:14+00:00",
          "url": "https://x.com/annieposting/status/1939768461229711697",
          "proof_of_search": "Community Archive row → normalized post → topic planet. Terms: good, really, bad, thing."
        },
        {
          "id": "art_b361870a59f7",
          "title": "Good receipt from 2025-06-13",
          "excerpt": "RT @growing_daniel: lmao they're so good at this. \"ohhh israel is so evil\" bro it's amazing restraint Israel lets Islamic countries hold an…",
          "source_document_id": "1933347372945560047",
          "timestamp": "2025-06-13T02:15:08+00:00",
          "url": "https://x.com/annieposting/status/1933347372945560047",
          "proof_of_search": "Community Archive row → normalized post → topic planet. Terms: good, really, bad, thing."
        },
        {
          "id": "art_da7765b00d2a",
          "title": "Good receipt from 2021-03-01",
          "excerpt": "Good Night https://t.co/IYnh2mBjJ3",
          "source_document_id": "1366185711318093824",
          "timestamp": "2021-03-01T00:37:10+00:00",
          "url": "https://x.com/annieposting/status/1366185711318093824",
          "proof_of_search": "Community Archive row → normalized post → topic planet. Terms: good, really, bad, thing."
        }
      ],
      "artifact_count": 4,
      "receipt_id": "rcpt_ccea1d7aae80",
      "proof_score": 1,
      "mass": 22.834,
      "color": "#8b5cf6",
      "cluster_id": 2,
      "density": 0.8175,
      "semantic_density": 0.8175,
      "semantic_dispersion": 0.1825,
      "embedding": [
        0.0,
        -0.052494,
        0.0,
        0.0,
        0.023376,
        -0.028536,
        0.0,
        0.057072,
        -0.031497,
        0.0,
        0.029119,
        0.029119,
        0.058237,
        0.0,
        0.0,
        0.0,
        0.0,
        -0.03537,
        0.0,
        0.195429,
        0.035106,
        0.0,
        0.0,
        0.0,
        0.028536,
        0.0,
        0.119358,
        -0.148476,
        0.0,
        0.035106,
        0.0,
        -0.195429,
        0.0,
        -0.028536,
        0.0,
        0.029119,
        0.046952,
        0.0,
        0.148476,
        0.0,
        0.0,
        0.0,
        -0.064225,
        0.060615,
        -0.067472,
        0.028536,
        0.148476,
        0.0,
        -0.868588,
        -0.000583,
        0.035106,
        0.0,
        -0.218208,
        0.0,
        0.028536,
        0.049478,
        0.029119,
        0.0,
        0.0,
        0.0,
        -0.028536,
        0.0,
        0.0,
        0.0
      ],
      "embedding_backend": "stable-token-hash-v1",
      "embedding_dimensions": 64,
      "embedding_document_count": 15,
      "mass_rule": "blended historical topic volume with stable-token-hash embedding density; compact semantic clusters pull harder than diffuse receipt piles",
      "mass_rank": 4,
      "mass_share_of_sun": 0.13976,
      "relative_mass_to_largest_planet": 0.80986,
      "radius_scale": 0.95196
    },
    {
      "id": "planet_82b885ea61d7",
      "name": "Only",
      "summary": "Archive cluster around only: 887 posts; 4 quote-backed receipts pinned.",
      "top_terms": [
        "only",
        "thing",
        "way",
        "could",
        "time"
      ],
      "artifacts": [
        {
          "id": "art_2f92d2c0e956",
          "title": "Only receipt from 2024-04-27",
          "excerpt": "i'm literally the highest value housewife, im constantly abusing stimulants and I'm a fantastic cook so im effectively a free maid and personal chef and I only have to eat every other day, she would barely have to spend more each week on groceries et al",
          "source_document_id": "1784360945030213831",
          "timestamp": "2024-04-27T23:16:15+00:00",
          "url": "https://x.com/annieposting/status/1784360945030213831",
          "proof_of_search": "Community Archive row → normalized post → topic planet. Terms: only, thing, way, could."
        },
        {
          "id": "art_429cc2053d9a",
          "title": "Only receipt from 2025-12-23",
          "excerpt": "RT @flugenhof: The worst part about being a white slave is the only field songs we know are by The Lumineers",
          "source_document_id": "2003314977873269231",
          "timestamp": "2025-12-23T04:01:25+00:00",
          "url": "https://x.com/annieposting/status/2003314977873269231",
          "proof_of_search": "Community Archive row → normalized post → topic planet. Terms: only, thing, way, could."
        },
        {
          "id": "art_9e996e45b3cf",
          "title": "Only receipt from 2026-06-09",
          "excerpt": "@alloftheeenergy I only saw the pfp and was like\n\n\"this might be the best elon post I've ever seen. he has never been this relatable before\"",
          "source_document_id": "2064408964130095599",
          "timestamp": "2026-06-09T18:07:06+00:00",
          "url": "https://x.com/annieposting/status/2064408964130095599",
          "proof_of_search": "Community Archive row → normalized post → topic planet. Terms: only, thing, way, could."
        },
        {
          "id": "art_24647093207f",
          "title": "Only receipt from 2026-06-03",
          "excerpt": "for the purposes of posting this I should note I both have no idea what he could possibly be referring to because I have done nothing wrong whatsoever, and I only posted this after Austin confirmed I would not be receiving any information",
          "source_document_id": "2062009843595293155",
          "timestamp": "2026-06-03T03:13:51+00:00",
          "url": "https://x.com/annieposting/status/2062009843595293155",
          "proof_of_search": "Community Archive row → normalized post → topic planet. Terms: only, thing, way, could."
        }
      ],
      "artifact_count": 4,
      "receipt_id": "rcpt_db483dece509",
      "proof_score": 1,
      "mass": 23.569,
      "color": "#06b6d4",
      "cluster_id": 3,
      "density": 0.8705,
      "semantic_density": 0.8705,
      "semantic_dispersion": 0.1295,
      "embedding": [
        0.043283,
        -0.019011,
        -0.02597,
        0.02597,
        0.027668,
        -0.017313,
        0.0,
        -0.017643,
        -0.008657,
        0.0,
        0.0,
        0.0,
        0.02597,
        0.00033,
        -0.046092,
        0.0,
        -0.017643,
        -0.00033,
        0.046092,
        -0.017643,
        0.034956,
        -0.046092,
        -0.017973,
        -0.017643,
        0.0,
        -0.035286,
        0.958008,
        -0.096174,
        0.0,
        0.0,
        0.0,
        0.05194,
        0.051316,
        0.0,
        0.036775,
        0.0,
        0.028449,
        0.008327,
        0.041755,
        -0.017313,
        0.0,
        0.0,
        -0.035286,
        0.02597,
        -0.044981,
        0.017313,
        0.096174,
        -0.017643,
        0.028449,
        0.0,
        0.028449,
        -0.017313,
        -0.130176,
        -0.011135,
        0.0,
        0.0,
        0.0,
        0.12152,
        0.0,
        0.0,
        0.0,
        0.0,
        0.0,
        0.0
      ],
      "embedding_backend": "stable-token-hash-v1",
      "embedding_dimensions": 64,
      "embedding_document_count": 15,
      "mass_rule": "blended historical topic volume with stable-token-hash embedding density; compact semantic clusters pull harder than diffuse receipt piles",
      "mass_rank": 2,
      "mass_share_of_sun": 0.14426,
      "relative_mass_to_largest_planet": 0.83593,
      "radius_scale": 0.95886
    },
    {
      "id": "planet_c660dfdf5569",
      "name": "Time",
      "summary": "Archive cluster around time: 774 posts; 4 quote-backed receipts pinned.",
      "top_terms": [
        "time",
        "every",
        "first",
        "free",
        "most"
      ],
      "artifacts": [
        {
          "id": "art_4f8b8653efe1",
          "title": "Time receipt from 2025-05-10",
          "excerpt": "RT @wrappedaroundme: Alcoholics be like it’s 8am time to make myself really fun and relaxed and awesome",
          "source_document_id": "1921002725824729269",
          "timestamp": "2025-05-10T00:41:54+00:00",
          "url": "https://x.com/annieposting/status/1921002725824729269",
          "proof_of_search": "Community Archive row → normalized post → topic planet. Terms: time, every, first, free."
        },
        {
          "id": "art_16a640b2fa8d",
          "title": "Time receipt from 2025-07-29",
          "excerpt": "RT @redaction: What the fuck prompted Every Single Western Government to start passing child safety legislation at the exact same time\n\nI’m…",
          "source_document_id": "1950330536385519680",
          "timestamp": "2025-07-29T23:00:09+00:00",
          "url": "https://x.com/annieposting/status/1950330536385519680",
          "proof_of_search": "Community Archive row → normalized post → topic planet. Terms: time, every, first, free."
        },
        {
          "id": "art_3fe4369388c6",
          "title": "Time receipt from 2025-04-25",
          "excerpt": "RT @fauxbeatpoet: “Can’t, I might get laid” has been the get-out-of-jail pass from time immemorial. What kind of question is this? Have peo…",
          "source_document_id": "1915637611634516286",
          "timestamp": "2025-04-25T05:22:52+00:00",
          "url": "https://x.com/annieposting/status/1915637611634516286",
          "proof_of_search": "Community Archive row → normalized post → topic planet. Terms: time, every, first, free."
        },
        {
          "id": "art_d4f96540d02f",
          "title": "Time receipt from 2026-05-24",
          "excerpt": "RT @wormpuller: Life hack: Get really fucked up every time you drink, drink way too much. Drink past the point of it being fun and embarras…",
          "source_document_id": "2058667698721321418",
          "timestamp": "2026-05-24T21:53:22+00:00",
          "url": "https://x.com/annieposting/status/2058667698721321418",
          "proof_of_search": "Community Archive row → normalized post → topic planet. Terms: time, every, first, free."
        }
      ],
      "artifact_count": 4,
      "receipt_id": "rcpt_f45d5dac5bce",
      "proof_score": 1,
      "mass": 22.684,
      "color": "#f43f5e",
      "cluster_id": 4,
      "density": 0.8343,
      "semantic_density": 0.8343,
      "semantic_dispersion": 0.1657,
      "embedding": [
        0.0,
        -0.049859,
        0.092549,
        0.0,
        0.024112,
        -0.031534,
        0.0,
        0.0,
        0.061003,
        0.0,
        0.061015,
        0.0,
        0.0,
        -0.025759,
        -0.025747,
        0.0,
        0.0,
        0.0,
        -0.036304,
        -0.185619,
        0.025747,
        -0.031534,
        0.0,
        0.0,
        0.0,
        -0.031534,
        0.19253,
        -0.141024,
        -0.025759,
        0.031522,
        -0.057281,
        -0.092549,
        0.852369,
        0.0,
        0.0,
        -0.185619,
        0.0,
        -0.061003,
        0.115265,
        0.025759,
        0.025759,
        0.0,
        0.035256,
        0.0,
        -0.024112,
        0.0,
        0.141024,
        0.0,
        -0.025759,
        0.0,
        0.025747,
        0.0,
        0.0,
        -0.035256,
        0.025747,
        -0.070343,
        0.0,
        -0.057281,
        0.0,
        0.0,
        0.237126,
        0.0,
        0.0,
        -0.031534
      ],
      "embedding_backend": "stable-token-hash-v1",
      "embedding_dimensions": 64,
      "embedding_document_count": 15,
      "mass_rule": "blended historical topic volume with stable-token-hash embedding density; compact semantic clusters pull harder than diffuse receipt piles",
      "mass_rank": 5,
      "mass_share_of_sun": 0.13884,
      "relative_mass_to_largest_planet": 0.80454,
      "radius_scale": 0.95054
    },
    {
      "id": "planet_710c8951531e",
      "name": "Should",
      "summary": "Archive cluster around should: 692 posts; 4 quote-backed receipts pinned.",
      "top_terms": [
        "should",
        "say",
        "party",
        "every",
        "person"
      ],
      "artifacts": [
        {
          "id": "art_e65341857257",
          "title": "Should receipt from 2026-04-19",
          "excerpt": "almost no social interaction should make you anxious, you just internalized social punishment from childhood. these situations are not meant to make you nervous at all it's unusual that they do",
          "source_document_id": "2045953210737991930",
          "timestamp": "2026-04-19T19:50:32+00:00",
          "url": "https://x.com/annieposting/status/2045953210737991930",
          "proof_of_search": "Community Archive row → normalized post → topic planet. Terms: should, say, party, every."
        },
        {
          "id": "art_8ab04f0674ff",
          "title": "Should receipt from 2025-07-14",
          "excerpt": "RT @FilledwithUrine: you should be allowed to call out of work if you dreamt of hugging a girl and spun around with her in your arms",
          "source_document_id": "1944665866664346057",
          "timestamp": "2025-07-14T07:50:47+00:00",
          "url": "https://x.com/annieposting/status/1944665866664346057",
          "proof_of_search": "Community Archive row → normalized post → topic planet. Terms: should, say, party, every."
        },
        {
          "id": "art_159fa21fd1ce",
          "title": "Should receipt from 2026-06-24",
          "excerpt": "my position on the vibecamp nudity debate is that skinny dipping should be allowed for women 24/7 but men never send tweet",
          "source_document_id": "2069880367717511567",
          "timestamp": "2026-06-24T20:28:30+00:00",
          "url": "https://x.com/annieposting/status/2069880367717511567",
          "proof_of_search": "Community Archive row → normalized post → topic planet. Terms: should, say, party, every."
        },
        {
          "id": "art_554051417dec",
          "title": "Should receipt from 2025-09-16",
          "excerpt": "RT @ManDaveJobGood: RW GCs: \"I guess after 10 years in the same GC I should probably tell you guys what state I live in.\"\n\nLeftoid GCs: \"Ne…",
          "source_document_id": "1967825276626477289",
          "timestamp": "2025-09-16T05:38:01+00:00",
          "url": "https://x.com/annieposting/status/1967825276626477289",
          "proof_of_search": "Community Archive row → normalized post → topic planet. Terms: should, say, party, every."
        }
      ],
      "artifact_count": 4,
      "receipt_id": "rcpt_fe640f2675b6",
      "proof_score": 1,
      "mass": 22.436,
      "color": "#84cc16",
      "cluster_id": 5,
      "density": 0.8284,
      "semantic_density": 0.8284,
      "semantic_dispersion": 0.1716,
      "embedding": [
        0.0,
        -0.050747,
        -0.027586,
        0.0,
        0.050747,
        0.07123,
        0.033831,
        0.0,
        -0.027586,
        0.0,
        0.0,
        -0.029882,
        0.027586,
        0.0,
        0.0,
        0.0,
        0.033831,
        0.0,
        0.0,
        0.0,
        0.0,
        0.032095,
        -0.027586,
        0.033831,
        0.0,
        -0.032095,
        0.113651,
        -0.143533,
        0.0,
        0.029882,
        -0.025373,
        -0.004509,
        0.029882,
        0.036044,
        -0.027586,
        0.0,
        0.032095,
        0.0,
        0.111438,
        -0.87053,
        0.0,
        0.250339,
        -0.029882,
        0.0,
        -0.050747,
        0.0,
        0.143533,
        -0.004509,
        0.0,
        -0.07922,
        0.027586,
        -0.029882,
        -0.033831,
        -0.188922,
        0.029882,
        0.0,
        0.0,
        -0.032095,
        -0.033831,
        0.0,
        0.188922,
        -0.027586,
        0.0,
        0.0
      ],
      "embedding_backend": "stable-token-hash-v1",
      "embedding_dimensions": 64,
      "embedding_document_count": 15,
      "mass_rule": "blended historical topic volume with stable-token-hash embedding density; compact semantic clusters pull harder than diffuse receipt piles",
      "mass_rank": 6,
      "mass_share_of_sun": 0.13732,
      "relative_mass_to_largest_planet": 0.79574,
      "radius_scale": 0.94818
    }
  ],
  "provenance": {
    "builder": "community-solar-systems-factory",
    "source": "Community Archive raw archive + Supabase incremental dumps",
    "archive_file": "data/archive.json",
    "archive_posts": "data/archive_posts.jsonl",
    "updates_dir": "data/updates",
    "merged_posts": "data/merged_posts.jsonl",
    "trust_os_mapping": {
      "sun": "account corpus gravity center",
      "planet": "visitable topic cluster",
      "artifact": "dated quote-backed archive receipt"
    },
    "embedding_metrics": {
      "schema": "community-solar-embeddings/v1",
      "generated_at": "2026-06-29T18:01:32.147334+00:00",
      "backend": "stable-token-hash-v1",
      "dimensions": 64,
      "privacy_boundary": "derived from public Community Archive text already present in this repository; no persistent identity capture added"
    }
  }
}
